Workbook

Sheet Resumen
B2: Plan de trabajo — Plataforma de administración de condominios (Vivecom) — México
B3: Administración, comunicación, seguridad y pagos en una sola plataforma, enfocada en el mercado mexicano
B5: Fecha de inicio del proyecto (editable): | D5: 46273
B8: Resumen de fases
B9: Fase | C9: Duración estimada | D9: Semanas | E9: Objetivo principal
B10: Fase 0 — Discovery y diseño | C10: 3 semanas | D10: 1-3 | E10: Definir alcance, arquitectura, UX y base de infraestructura
B11: Fase 1 — MVP | C11: 9 semanas | D11: 4-12 | E11: Administrativo (cuotas y pagos) + Comunicación básica en producción
B12: Fase 2 — Diferenciación | C12: 10 semanas | D12: 13-22 | E12: Seguridad (accesos/incidencias) + Comunicación avanzada + Amenidades
B13: Fase 3 — Escala | C13: Continuo | D13: 23+ | E13: Métodos de pago adicionales (SPEI), cumplimiento de datos, integraciones y crecimiento nacional
B16: Carga de trabajo total por fase (días-persona)
B17: Fase | C17: Total días-persona | D17: N° de tareas
B18: Fase 0 | C18: =SUMIF('Plan de trabajo'!B:B,B18,'Plan de trabajo'!G:G) -> 56 | D18: =COUNTIF('Plan de trabajo'!B:B,B18) -> 17
B19: Fase 1 | C19: =SUMIF('Plan de trabajo'!B:B,B19,'Plan de trabajo'!G:G) -> 126 | D19: =COUNTIF('Plan de trabajo'!B:B,B19) -> 39
B20: Fase 2 | C20: =SUMIF('Plan de trabajo'!B:B,B20,'Plan de trabajo'!G:G) -> 91 | D20: =COUNTIF('Plan de trabajo'!B:B,B20) -> 23
B21: Fase 3 | C21: =SUMIF('Plan de trabajo'!B:B,B21,'Plan de trabajo'!G:G) -> 27 | D21: =COUNTIF('Plan de trabajo'!B:B,B21) -> 6
B22: Total proyecto | C22: =SUM(C18:C21) -> 300 | D22: =SUM(D18:D21) -> 85
B25: Carga de trabajo por rol (días-persona)
B26: Rol | C26: Total días-persona
B27: PM / Producto | C27: =SUMIF('Plan de trabajo'!F:F,B27,'Plan de trabajo'!G:G) -> 22
B28: UX/UI | C28: =SUMIF('Plan de trabajo'!F:F,B28,'Plan de trabajo'!G:G) -> 19
B29: Tech Lead | C29: =SUMIF('Plan de trabajo'!F:F,B29,'Plan de trabajo'!G:G) -> 14
B30: Backend | C30: =SUMIF('Plan de trabajo'!F:F,B30,'Plan de trabajo'!G:G) -> 134
B31: Frontend | C31: =SUMIF('Plan de trabajo'!F:F,B31,'Plan de trabajo'!G:G) -> 34
B32: Mobile | C32: =SUMIF('Plan de trabajo'!F:F,B32,'Plan de trabajo'!G:G) -> 41
B33: DevOps | C33: =SUMIF('Plan de trabajo'!F:F,B33,'Plan de trabajo'!G:G) -> 22
B34: QA | C34: =SUMIF('Plan de trabajo'!F:F,B34,'Plan de trabajo'!G:G) -> 14
B35: Legal/Cumplimiento | C35: =SUMIF('Plan de trabajo'!F:F,B35,'Plan de trabajo'!G:G) -> 0

Sheet Plan de trabajo
A1: ID | B1: Fase | C1: Módulo | D1: Tarea | E1: Descripción | F1: Rol responsable | G1: Estimación (días) | H1: Prioridad | I1: Dependencia (ID) | J1: Semana estimada | K1: Estado
A2: F0-01 | B2: Fase 0 | C2: Producto | D2: Definir alcance detallado del MVP | E2: Documentar historias de usuario y criterios de aceptación para Fase 1. | F2: PM / Producto | G2: 3 | H2: Alta | J2: 1 | K2: Pendiente
A3: F0-02 | B3: Fase 0 | C3: Producto | D3: Investigación de competidores | E3: Analizar Comunidad Feliz, TrustCondo, Kiper y similares: features, precios, huecos de mercado. | F3: PM / Producto | G3: 3 | H3: Media | J3: 1 | K3: Pendiente
A4: F0-03 | B4: Fase 0 | C4: Producto | D4: Entrevistas con administradores potenciales | E4: 5-10 entrevistas para validar dolor real y disposición de pago. | F4: PM / Producto | G4: 4 | H4: Alta | J4: 1 | K4: Pendiente
A5: F0-04 | B5: Fase 0 | C5: Producto | D5: Definir modelo de negocio y pricing | E5: Cobro por vivienda, periodicidad mensual, sin periodo de prueba gratuito (ya definido en el alcance). | F5: PM / Producto | G5: 2 | H5: Alta | J5: 2 | K5: Pendiente
A6: F0-05 | B6: Fase 0 | C6: Arquitectura | D6: Elegir stack tecnológico definitivo | E6: Confirmar backend, frontend, mobile, BD, infraestructura cloud y proveedor de recepción SPEI. | F6: Tech Lead | G6: 2 | H6: Alta | J6: 1 | K6: Pendiente
A7: F0-06 | B7: Fase 0 | C7: Arquitectura | D7: Diseñar estrategia multi-tenant | E7: Definir schema-por-tenant en PostgreSQL, aislamiento de datos y ruteo por tenant. | F7: Tech Lead | G7: 3 | H7: Alta | J7: 2 | K7: Pendiente
A8: F0-07 | B8: Fase 0 | C8: Arquitectura | D8: Diseñar modelo de datos (ERD) completo | E8: Modelar Tenant, Property, Resident, Fee, Payment, AccessLog, Incident, Announcement, Poll, Reservation. | F8: Tech Lead | G8: 4 | H8: Alta | J8: 2 | K8: Pendiente
A9: F0-08 | B9: Fase 0 | C9: UX/UI | D9: Mapear flujos de usuario | E9: Flujos clave: residente paga cuota, admin envía aviso, guardia registra visitante. | F9: UX/UI | G9: 3 | H9: Alta | J9: 1 | K9: Pendiente
A10: F0-09 | B10: Fase 0 | C10: UX/UI | D10: Wireframes de baja fidelidad | E10: Wireframes de app residente, panel admin y app caseta. | F10: UX/UI | G10: 5 | H10: Alta | J10: 2 | K10: Pendiente
A11: F0-10 | B11: Fase 0 | C11: UX/UI | D11: Sistema de diseño y UI kit | E11: Paleta, tipografía, componentes reutilizables para las 3 plataformas. | F11: UX/UI | G11: 4 | H11: Media | J11: 2 | K11: Pendiente
A12: F0-11 | B12: Fase 0 | C12: UX/UI | D12: Prototipo navegable en Figma | E12: Prototipo de alta fidelidad de los flujos críticos del MVP. | F12: UX/UI | G12: 5 | H12: Alta | I12: F0-09 | J12: 3 | K12: Pendiente
A13: F0-12 | B13: Fase 0 | C13: UX/UI | D13: Validación de prototipo con administradores | E13: Sesiones de usabilidad con 3-5 administradores reales. | F13: UX/UI | G13: 2 | H13: Media | I13: F0-11 | J13: 3 | K13: Pendiente
A14: F0-13 | B14: Fase 0 | C14: Infraestructura | D14: Configurar repositorios y estrategia de branching | E14: Monorepo o multi-repo, convenciones de commits, protección de ramas. | F14: DevOps | G14: 1 | H14: Alta | J14: 1 | K14: Pendiente
A15: F0-14 | B15: Fase 0 | C15: Infraestructura | D15: Configurar CI/CD | E15: Pipelines de build, test y deploy automático a staging. | F15: DevOps | G15: 3 | H15: Alta | I15: F0-13 | J15: 2 | K15: Pendiente
A16: F0-15 | B16: Fase 0 | C16: Infraestructura | D16: Levantar entornos dev/staging/producción | E16: Infraestructura en AWS/GCP región LATAM (México). | F16: DevOps | G16: 4 | H16: Alta | J16: 2 | K16: Pendiente
A17: F0-16 | B17: Fase 0 | C17: Infraestructura | D17: Definir infraestructura como código (Terraform) | E17: Scripts reproducibles para levantar entornos. | F17: DevOps | G17: 3 | H17: Media | I17: F0-15 | J17: 3 | K17: Pendiente
A18: F0-17 | B18: Fase 0 | C18: Backend | D18: Implementar autenticación multi-tenant | E18: JWT, roles (admin, tesorero, comité, vocero, residente, guardia) y aislamiento por tenant. | F18: Backend | G18: 5 | H18: Alta | I18: F0-06,F0-07 | J18: 3 | K18: Pendiente
A19: F1-01 | B19: Fase 1 | C19: Administrativo | D19: CRUD de Tenant, Property y Resident | E19: Alta de condominios, viviendas y residentes con relación N:N (propietario/inquilino); cada vivienda se administra de forma independiente. | F19: Backend | G19: 5 | H19: Alta | I19: F0-07,F0-17 | J19: 4 | K19: Pendiente
A20: F1-02 | B20: Fase 1 | C20: Administrativo | D20: Módulo de configuración de cuotas (Fee) | E20: Definir monto y periodicidad por condominio; el recargo por mora es una regla global de la plataforma. | F20: Backend | G20: 4 | H20: Alta | I20: F1-01 | J20: 4 | K20: Pendiente
A21: F1-03 | B21: Fase 1 | C21: Administrativo | D21: Generación automática de cargos mensuales | E21: Job programado que crea FeeCharge por vivienda cada ciclo. | F21: Backend | G21: 3 | H21: Alta | I21: F1-02 | J21: 5 | K21: Pendiente
A22: F1-04 | B22: Fase 1 | C22: Administrativo | D22: Cálculo de recargos por mora | E22: Regla global: 10% aplicado a partir del minuto 1 del día 6 de cada mes (5 días de gracia). | F22: Backend | G22: 3 | H22: Media | I22: F1-03 | J22: 5 | K22: Pendiente
A23: F1-05 | B23: Fase 1 | C23: Administrativo | D23: Configuración de cuenta CLABE de destino | E23: El administrador define/cambia la CLABE del condominio con confirmación explícita y bitácora de auditoría. | F23: Backend | G23: 3 | H23: Alta | I23: F1-01 | J23: 5 | K23: Pendiente
A24: F1-06 | B24: Fase 1 | C24: Administrativo | D24: Integración de recepción de pagos vía SPEI | E24: Proveedor de recepción SPEI (ej. STP/Arcus) para generar cobro por CLABE y detectar depósitos entrantes (sin Open Banking ni iniciación de transferencia). | F24: Backend | G24: 6 | H24: Alta | I24: F1-05 | J24: 6 | K24: Pendiente
A25: F1-07 | B25: Fase 1 | C25: Administrativo | D25: Conciliación automática de pagos | E25: Procesar notificaciones del proveedor SPEI y marcar cada transferencia como confirmada, pendiente o rechazada, conciliando contra FeeCharge. | F25: Backend | G25: 4 | H25: Alta | I25: F1-06,F1-03 | J25: 6 | K25: Pendiente
A26: F1-08 | B26: Fase 1 | C26: Administrativo | D26: Pago anticipado (1 a 12 meses) | E26: Permitir aplicar un pago a varios cargos futuros en una sola operación, evitando recargos futuros. | F26: Backend | G26: 3 | H26: Media | I26: F1-07 | J26: 7 | K26: Pendiente
A27: F1-09 | B27: Fase 1 | C27: Administrativo | D27: Cálculo y aplicación de saldo a favor | E27: Si el monto transferido excede lo debido, el excedente se guarda y aplica automáticamente al siguiente cargo. | F27: Backend | G27: 3 | H27: Media | I27: F1-07 | J27: 7 | K27: Pendiente
A28: F1-10 | B28: Fase 1 | C28: Administrativo | D28: Panel de validación de pagos (tesorero) | E28: Vista para que el tesorero confirme pagos detectados y resuelva casos especiales (rechazos, ajustes). | F28: Backend | G28: 3 | H28: Alta | I28: F1-07 | J28: 7 | K28: Pendiente
... A86: F3-06 | B86: Fase 3 | C86: Comercial | D86: Onboarding self-service para nuevos condominios | E86: Flujo de alta de condominio sin intervención manual del equipo. | F86: Frontend | G86: 5 | H86: Media | I86: F1-01 | J86: 25 | K86: Pendiente

Sheet Hitos
B2: Hitos clave del proyecto
B3: Las fechas se calculan a partir de la fecha de inicio definida en la hoja Resumen (celda D5).
B5: Hito | C5: Semana | D5: Fecha estimada
B6: Fin de Fase 0 — Arquitectura y diseño aprobados | C6: 3 | D6: =Resumen!$D$5+(C6*7) -> 46294
B7: Módulo de cuotas y pagos en staging | C7: 6 | D7: =Resumen!$D$5+(C7*7) -> 46315
B8: MVP administrativo + comunicación listo para beta cerrada | C8: 9 | D8: =Resumen!$D$5+(C8*7) -> 46336
B9: Inicio de beta cerrada con 2-3 condominios piloto | C9: 9 | D9: =Resumen!$D$5+(C9*7) -> 46336
B10: Módulo de seguridad y control de accesos en staging | C10: 17 | D10: =Resumen!$D$5+(C10*7) -> 46392
B11: Reservaciones y votaciones en staging | C11: 21 | D11: =Resumen!$D$5+(C11*7) -> 46420
B12: Fin de Fase 2 — Inicio de beta ampliada (10-15 condominios) | C12: 22 | D12: =Resumen!$D$5+(C12*7) -> 46427
B13: Cumplimiento LFPDPPP, BI y exportación contable en producción | C13: 24 | D13: =Resumen!$D$5+(C13*7) -> 46441
B14: Lanzamiento comercial general en México (GA) | C14: 25 | D14: =Resumen!$D$5+(C14*7) -> 46448
